progressbar/__init__.py
progressbar/progressbar.py
progressbarlib-1.0.0.dist-info/METADATA
progressbarlib-1.0.0.dist-info/WHEEL
progressbarlib-1.0.0.dist-info/top_level.txt
progressbarlib-1.0.0.dist-info/RECORD
